{
"framework":"AppConKit",
"url":"http://www.weptun.com",
"framework_current_version":"1.1",
"comparison_data_last_update":"04.26.2012",
"ios":"true",
"android":"true",
 
"windowsphone":"soon",
 
 
 
 
 
 
 
 
 
"nativeapp":"true",
"hybridapp":"true",
"php":"true",
"java":"true",
"ruby":"soon",
"actionscript":"",
"csharp":"soon",
"lua":"",
"html":"",
"css":"",
"js":"via",
"cplusplus":"",
"visualeditor":"true",
"accelerometer":"soon",
"camera":"true",
"capture":"true",
"compass":"soon",
"connection":"true",
"contacts":"true",
"device":"true",
"nativeevents":"true",
"file":"true",
"geolocation":"true",
"notification":"true",
"storage":"true",
"gestures_multitouch":"true",
"messages_telephone":"true",
"bluetooth":"via",
"nfc":"soon",
"vibration":"true",
"cd":"partially",
"widgets":"true",
"accessibility":"true",
"sdk":"soon",
"encryption":"true",
"ads":"soon",
"free":"true",
"opensource":""
}